flaskr/__init__.py
flaskr/auth.py
flaskr/blog.py
flaskr/db.py
flaskr/schema.sql
flaskr/static/styles.css
flaskr/templates/base.html
flaskr/templates/auth/login.html
flaskr/templates/auth/register.html
flaskr/templates/blog/create.html
flaskr/templates/blog/index.html
flaskr/templates/blog/update.html
flaskr_robinm-1.1.0.dist-info/METADATA
flaskr_robinm-1.1.0.dist-info/WHEEL
flaskr_robinm-1.1.0.dist-info/top_level.txt
flaskr_robinm-1.1.0.dist-info/RECORD
