Metadata-Version: 2.1
Name: flaskr-robinm
Version: 1.1.0
Summary: UNKNOWN
Home-page: UNKNOWN
License: UNKNOWN
Platform: UNKNOWN
Requires-Dist: Flask
